nonebot_plugin_chatglm_plus/__init__.py
nonebot_plugin_chatglm_plus/config.py
nonebot_plugin_chatglm_plus-0.2.4.dist-info/METADATA
nonebot_plugin_chatglm_plus-0.2.4.dist-info/WHEEL
nonebot_plugin_chatglm_plus-0.2.4.dist-info/top_level.txt
nonebot_plugin_chatglm_plus-0.2.4.dist-info/RECORD
