Metadata-Version: 2.1
Name: nonebot-plugin-chatglm-plus
Version: 0.2.4
Summary: 人性化的ChatGLM插件，使用智谱API
Home-page: https://github.com/XTxiaoting14332/nonebot-plugin-chatglm-plus
Author: NightWind
Author-email: 2125714976@qq.com
License: UNKNOWN
Platform: UNKNOWN
Requires-Dist: PyJWT
Requires-Dist: httpx
Requires-Dist: nonebot-adapter-onebot
Requires-Dist: nonebot-plugin-localstore
Requires-Dist: nonebot-plugin-send-anything-anywhere
Requires-Dist: nonebot-plugin-session
Requires-Dist: nonebot2 (>=2.2.0)
